minibudget/__init__.py
minibudget/convert.py
minibudget/helpers.py
minibudget/minibudget.py
minibudget/model.py
minibudget/parse.py
minibudget/parsers.py
minibudget/render.py
minibudget/templates/diff.html
minibudget/transform.py
minibudget-2024.11.4.dist-info/METADATA
minibudget-2024.11.4.dist-info/WHEEL
minibudget-2024.11.4.dist-info/entry_points.txt
minibudget-2024.11.4.dist-info/RECORD
