Metadata-Version: 2.1
Name: minibudget
Version: 2024.11.4
Summary: A simple CLI tool for personal and small business budgeting.
Home-page: https://github.com/fdavies93/minibudget
License: AGPL-3.0-or-later
Keywords: minibudget,plaintext,plaintext-accounting,cli
Author: Frank Davies
Requires-Python: >=3.10,<4.0
Classifier: License :: OSI Approved :: GNU Affero General Public License v3 or later (AGPLv3+)
Classifier: Programming Language :: Python :: 3
Classifier: Programming Language :: Python :: 3.10
Classifier: Programming Language :: Python :: 3.11
Classifier: Programming Language :: Python :: 3.12
Classifier: Programming Language :: Python :: 3.13
Classifier: Topic :: Office/Business :: Financial
Provides-Extra: convert
Requires-Dist: beanquery (==0.1.*) ; extra == "convert"
Requires-Dist: jinja2 (>=3.1.4,<4.0.0)
Requires-Dist: plotly (>=5.24.1,<6.0.0)
Requires-Dist: rich (>=13.9.2,<14.0.0)
Project-URL: Repository, https://github.com/fdavies93/minibudget
